geo_api_gouv_fr/__init__.py
geo_api_gouv_fr/adress/__init__.py
geo_api_gouv_fr/adress/api.py
geo_api_gouv_fr/adress/schemas.py
geo_api_gouv_fr/cache.py
geo_api_gouv_fr/commune/__init__.py
geo_api_gouv_fr/commune/api.py
geo_api_gouv_fr/commune/schemas.py
geo_api_gouv_fr/department/__init__.py
geo_api_gouv_fr/department/api.py
geo_api_gouv_fr/department/schemas.py
geo_api_gouv_fr/region/__init__.py
geo_api_gouv_fr/region/api.py
geo_api_gouv_fr/region/schemas.py
geo_api_gouv_fr/tests/__init__.py
geo_api_gouv_fr/tests/data/lbb-search.csv
geo_api_gouv_fr/tests/data/reverse.csv
geo_api_gouv_fr/tests/data/search.csv
geo_api_gouv_fr/tests/test_adresse.py
geo_api_gouv_fr/tests/test_cache.py
geo_api_gouv_fr/tests/test_city.py
geo_api_gouv_fr/tests/test_commune.py
geo_api_gouv_fr/tests/test_department.py
geo_api_gouv_fr/tests/test_region.py
geo_api_gouv_fr-1.10.0.dist-info/METADATA
geo_api_gouv_fr-1.10.0.dist-info/WHEEL
geo_api_gouv_fr-1.10.0.dist-info/RECORD
