Metadata-Version: 2.3
Name: geo-api-gouv-fr
Version: 1.10.0
Summary: Python package to use geoapi.gouv.fr api
License: GPL-3.0-only
Keywords: geoapi,geoapi.gouv,geoapi.gouv.fr
Author: La Bonne Boite
Author-email: labonneboite@pole-emploi.fr
Requires-Python: >=3.11,<4.0
Classifier: Development Status :: 5 - Production/Stable
Classifier: License :: OSI Approved :: GNU Affero General Public License v3
Classifier: License :: OSI Approved :: GNU General Public License v3 (GPLv3)
Classifier: Programming Language :: Python
Classifier: Programming Language :: Python :: 3
Classifier: Programming Language :: Python :: 3.11
Classifier: Programming Language :: Python :: 3.12
Classifier: Programming Language :: Python :: 3.13
Classifier: Programming Language :: Python :: 3.10
Requires-Dist: pydantic (>=2.5.3,<3.0.0)
Requires-Dist: pytest-html (>=3.1.1,<4.0.0)
Requires-Dist: redis (>=5.0.3,<6.0.0)
Requires-Dist: requests (>=2.28.2,<3.0.0)
Requires-Dist: requests-cache (>=1.1.1,<2.0.0)
Project-URL: Repository, https://github.com/StartupsPoleEmploi/geo-api-gouv-fr
